keg/__init__.py
keg/app.py
keg/assets.py
keg/cli.py
keg/component.py
keg/config.py
keg/ctx.py
keg/extensions.py
keg/logging.py
keg/signals.py
keg/templating.py
keg/testing.py
keg/utils.py
keg/version.py
keg/web.py
keg/db/__init__.py
keg/db/dialect_ops.py
keg/tests/__init__.py
keg/tests/test_app.py
keg/tests/test_assets.py
keg/tests/test_cli.py
keg/tests/test_config.py
keg/tests/test_db.py
keg/tests/test_db_dialects.py
keg/tests/test_logging.py
keg/tests/test_templating.py
keg/tests/test_utils.py
keg/tests/test_view_routing.py
keg/tests/test_view_templating.py
keg/tests/test_web.py
keg_apps/__init__.py
keg_apps/cli.py
keg_apps/db2.py
keg_apps/extensions.py
keg_apps/logging.py
keg_apps/cli2/__init__.py
keg_apps/cli2/app.py
keg_apps/cli2/cli.py
keg_apps/db/__init__.py
keg_apps/db/app.py
keg_apps/db/config.py
keg_apps/db/user-config-tpl-appveyor.py
keg_apps/db/user-config-tpl.py
keg_apps/db/blog/__init__.py
keg_apps/db/blog/model/__init__.py
keg_apps/db/blog/model/entities.py
keg_apps/db/model/__init__.py
keg_apps/db/model/entities.py
keg_apps/profile/__init__.py
keg_apps/profile/app.py
keg_apps/profile/cli.py
keg_apps/profile/config.py
keg_apps/templating/__init__.py
keg_apps/templating/app.py
keg_apps/web/__init__.py
keg_apps/web/app.py
keg_apps/web/cli.py
keg_apps/web/config.py
keg_apps/web/blog/__init__.py
keg_apps/web/blog/views.py
keg_apps/web/views/__init__.py
keg_apps/web/views/custom.py
keg_apps/web/views/other.py
keg_apps/web/views/routing.py
keg_apps/web/views/templating.py
Keg-0.11.1.dist-info/METADATA
Keg-0.11.1.dist-info/WHEEL
Keg-0.11.1.dist-info/top_level.txt
Keg-0.11.1.dist-info/RECORD
