Metadata-Version: 2.1
Name: Keg
Version: 0.11.1
Summary: A web framework built on Flask & SQLAlchemy.  Somewhere North of Flask but South of Django.
Home-page: https://github.com/level12/keg
Author: Randy Syring
Author-email: randy.syring@level12.io
License: BSD
Platform: UNKNOWN
Classifier: Development Status :: 4 - Beta
Classifier: Intended Audience :: Developers
Classifier: License :: OSI Approved :: BSD License
Classifier: Operating System :: OS Independent
Classifier: Programming Language :: Python :: 3
Classifier: Programming Language :: Python :: 3.7
Classifier: Programming Language :: Python :: 3.8
Classifier: Programming Language :: Python :: 3.9
Classifier: Programming Language :: Python :: 3.10
Requires-Dist: appdirs
Requires-Dist: BlazeUtils
Requires-Dist: blinker
Requires-Dist: Click (>=3.0)
Requires-Dist: Flask
Requires-Dist: Flask-SQLAlchemy
Requires-Dist: python-json-logger
Requires-Dist: sqlalchemy
Provides-Extra: i18n
Requires-Dist: morphi (>=0.2.0) ; extra == 'i18n'
Provides-Extra: tests
Requires-Dist: flask-webtest ; extra == 'tests'
Requires-Dist: flask-wtf ; extra == 'tests'
Requires-Dist: sqlalchemy-pyodbc-mssql ; extra == 'tests'
Requires-Dist: pyodbc (==4.0.34) ; extra == 'tests'
Requires-Dist: pytest ; extra == 'tests'
Requires-Dist: pytest-cov ; extra == 'tests'
Requires-Dist: python-dotenv ; extra == 'tests'
Requires-Dist: psycopg2-binary ; extra == 'tests'
Requires-Dist: mock ; extra == 'tests'
